{
    "codeToName": {
        "5": "breve",
        "6": "dotaccent",
        "7": ".notdef",
        "8": "ring",
        "10": "hungarumlaut",
        "11": "ogonek",
        "12": "caron",
        "13": "dotlessi",
        "25": "fraction",
        "26": "fi",
        "27": "fl",
        "28": "Lslash",
        "29": "lslash",
        "30": "Zcaron",
        "31": "zcaron",
        "32": "space",
        "33": "exclam",
        "34": "quotedbl",
        "35": "numbersign",
        "36": "dollar",
        "37": "percent",
        "38": "ampersand",
        "39": "quotesingle",
        "40": "parenleft",
        "41": "parenright",
        "42": "asterisk",
        "43": "plus",
        "44": "comma",
        "45": "hyphen",
        "46": "period",
        "47": "slash",
        "48": "zero",
        "49": "one",
        "50": "two",
        "51": "three",
        "52": "four",
        "53": "five",
        "54": "six",
        "55": "seven",
        "56": "eight",
        "57": "nine",
        "58": "colon",
        "59": "semicolon",
        "60": "less",
        "61": "equal",
        "62": "greater",
        "63": "question",
        "64": "at",
        "65": "A",
        "66": "B",
        "67": "C",
        "68": "D",
        "69": "E",
        "70": "F",
        "71": "G",
        "72": "H",
        "73": "I",
        "74": "J",
        "75": "K",
        "76": "L",
        "77": "M",
        "78": "N",
        "79": "O",
        "80": "P",
        "81": "Q",
        "82": "R",
        "83": "S",
        "84": "T",
        "85": "U",
        "86": "V",
        "87": "W",
        "88": "X",
        "89": "Y",
        "90": "Z",
        "91": "bracketleft",
        "92": "backslash",
        "93": "bracketright",
        "94": "asciicircum",
        "95": "underscore",
        "96": "grave",
        "97": "a",
        "98": "b",
        "99": "c",
        "100": "d",
        "101": "e",
        "102": "f",
        "103": "g",
        "104": "h",
        "105": "i",
        "106": "j",
        "107": "k",
        "108": "l",
        "109": "m",
        "110": "n",
        "111": "o",
        "112": "p",
        "113": "q",
        "114": "r",
        "115": "s",
        "116": "t",
        "117": "u",
        "118": "v",
        "119": "w",
        "120": "x",
        "121": "y",
        "122": "z",
        "123": "braceleft",
        "124": "bar",
        "125": "braceright",
        "126": "asciitilde",
        "161": "exclamdown",
        "162": "cent",
        "163": "sterling",
        "164": "currency",
        "165": "yen",
        "166": "brokenbar",
        "167": "section",
        "168": "dieresis",
        "169": "copyright",
        "170": "ordfeminine",
        "171": "guillemotleft",
        "172": "logicalnot",
        "174": "registered",
        "175": "macron",
        "176": "degree",
        "177": "plusminus",
        "180": "acute",
        "181": "mu",
        "182": "paragraph",
        "183": "periodcentered",
        "184": "cedilla",
        "186": "ordmasculine",
        "187": "guillemotright",
        "191": "questiondown",
        "192": "Agrave",
        "193": "Aacute",
        "194": "Acircumflex",
        "195": "Atilde",
        "196": "Adieresis",
        "197": "Aring",
        "198": "AE",
        "199": "Ccedilla",
        "200": "Egrave",
        "201": "Eacute",
        "202": "Ecircumflex",
        "203": "Edieresis",
        "204": "Igrave",
        "205": "Iacute",
        "206": "Icircumflex",
        "207": "Idieresis",
        "209": "Ntilde",
        "210": "Ograve",
        "211": "Oacute",
        "212": "Ocircumflex",
        "213": "Otilde",
        "214": "Odieresis",
        "215": "multiply",
        "216": "Oslash",
        "217": "Ugrave",
        "218": "Uacute",
        "219": "Ucircumflex",
        "220": "Udieresis",
        "221": "Yacute",
        "223": "germandbls",
        "224": "agrave",
        "225": "aacute",
        "226": "acircumflex",
        "227": "atilde",
        "228": "adieresis",
        "229": "aring",
        "230": "ae",
        "231": "ccedilla",
        "232": "egrave",
        "233": "eacute",
        "234": "ecircumflex",
        "235": "edieresis",
        "236": "igrave",
        "237": "iacute",
        "238": "icircumflex",
        "239": "idieresis",
        "241": "ntilde",
        "242": "ograve",
        "243": "oacute",
        "244": "ocircumflex",
        "245": "otilde",
        "246": "odieresis",
        "247": "divide",
        "248": "oslash",
        "249": "ugrave",
        "250": "uacute",
        "251": "ucircumflex",
        "252": "udieresis",
        "253": "yacute",
        "255": "ydieresis",
        "338": "OE",
        "339": "oe",
        "352": "Scaron",
        "353": "scaron",
        "376": "Ydieresis",
        "402": "florin",
        "710": "circumflex",
        "732": "tilde",
        "8211": "endash",
        "8212": "emdash",
        "8216": "quoteleft",
        "8217": "quoteright",
        "8218": "quotesinglbase",
        "8219": ".notdef",
        "8220": "quotedblleft",
        "8221": "quotedblright",
        "8222": "quotedblbase",
        "8223": ".notdef",
        "8224": "dagger",
        "8225": "daggerdbl",
        "8226": "bullet",
        "8230": "ellipsis",
        "8240": "perthousand",
        "8249": "guilsinglleft",
        "8250": "guilsinglright",
        "8482": "trademark",
        "8729": "periodcentered",
        "57344": "minus",
        "57345": "notequal",
        "57346": "infinity",
        "57347": "lessequal",
        "57348": "greaterequal",
        "57349": "partialdiff",
        "57350": "summation",
        "57351": "product",
        "57352": "pi",
        "57353": "integral",
        "57354": "Omega",
        "57355": "radical",
        "57356": "approxequal",
        "57357": "increment",
        "57358": "lozenge",
        "57359": "DST",
        "57360": "longs",
        "57361": "delta"
    },
    "isUnicode": true,
    "EncodingScheme": "FontSpecific",
    "FontName": "Canterbury",
    "FullName": "Canterbury Regular",
    "Version": "1.34",
    "PostScriptName": "Canterbury-Regular",
    "Weight": "Medium",
    "ItalicAngle": "0",
    "IsFixedPitch": "false",
    "UnderlineThickness": "50",
    "UnderlinePosition": "-80",
    "FontHeightOffset": "63",
    "Ascender": "695",
    "Descender": "-147",
    "FontBBox": [
        "-119",
        "-249",
        "1415",
        "917"
    ],
    "StartCharMetrics": "236",
    "C": {
        "5": 500,
        "6": 500,
        "7": 500,
        "8": 500,
        "10": 500,
        "11": 500,
        "12": 500,
        "13": 244,
        "25": 113,
        "26": 472,
        "27": 478,
        "28": 601,
        "29": 227,
        "30": 508,
        "31": 277,
        "32": 350,
        "33": 286,
        "34": 334,
        "35": 620,
        "36": 492,
        "37": 517,
        "38": 723,
        "39": 213,
        "40": 311,
        "41": 311,
        "42": 379,
        "43": 500,
        "44": 233,
        "45": 229,
        "46": 233,
        "47": 489,
        "48": 491,
        "49": 491,
        "50": 491,
        "51": 491,
        "52": 491,
        "53": 491,
        "54": 491,
        "55": 491,
        "56": 491,
        "57": 491,
        "58": 233,
        "59": 233,
        "60": 500,
        "61": 500,
        "62": 500,
        "63": 319,
        "64": 684,
        "65": 629,
        "66": 743,
        "67": 617,
        "68": 737,
        "69": 634,
        "70": 623,
        "71": 692,
        "72": 743,
        "73": 518,
        "74": 553,
        "75": 705,
        "76": 601,
        "77": 858,
        "78": 789,
        "79": 731,
        "80": 710,
        "81": 755,
        "82": 700,
        "83": 729,
        "84": 652,
        "85": 736,
        "86": 626,
        "87": 864,
        "88": 551,
        "89": 671,
        "90": 508,
        "91": 500,
        "92": 239,
        "93": 500,
        "94": 500,
        "95": 500,
        "96": 500,
        "97": 408,
        "98": 409,
        "99": 307,
        "100": 422,
        "101": 356,
        "102": 249,
        "103": 427,
        "104": 413,
        "105": 244,
        "106": 226,
        "107": 420,
        "108": 227,
        "109": 651,
        "110": 444,
        "111": 389,
        "112": 419,
        "113": 407,
        "114": 327,
        "115": 403,
        "116": 245,
        "117": 449,
        "118": 415,
        "119": 621,
        "120": 409,
        "121": 382,
        "122": 277,
        "123": 500,
        "124": 500,
        "125": 500,
        "126": 667,
        "161": 319,
        "162": 386,
        "163": 548,
        "164": 698,
        "165": 608,
        "166": 252,
        "167": 575,
        "168": 500,
        "169": 777,
        "170": 348,
        "171": 441,
        "172": 500,
        "174": 777,
        "175": 500,
        "176": 500,
        "177": 500,
        "180": 500,
        "181": 554,
        "182": 580,
        "183": 490,
        "184": 500,
        "186": 348,
        "187": 441,
        "191": 286,
        "192": 629,
        "193": 629,
        "194": 629,
        "195": 629,
        "196": 629,
        "197": 629,
        "198": 915,
        "199": 617,
        "200": 634,
        "201": 634,
        "202": 634,
        "203": 634,
        "204": 518,
        "205": 518,
        "206": 518,
        "207": 518,
        "209": 789,
        "210": 731,
        "211": 731,
        "212": 731,
        "213": 731,
        "214": 731,
        "215": 500,
        "216": 733,
        "217": 736,
        "218": 736,
        "219": 736,
        "220": 736,
        "221": 671,
        "223": 430,
        "224": 408,
        "225": 408,
        "226": 408,
        "227": 408,
        "228": 408,
        "229": 408,
        "230": 521,
        "231": 307,
        "232": 356,
        "233": 356,
        "234": 358,
        "235": 356,
        "236": 244,
        "237": 244,
        "238": 244,
        "239": 244,
        "241": 444,
        "242": 389,
        "243": 389,
        "244": 389,
        "245": 389,
        "246": 389,
        "247": 667,
        "248": 384,
        "249": 449,
        "250": 449,
        "251": 449,
        "252": 449,
        "253": 382,
        "255": 382,
        "338": 1070,
        "339": 537,
        "352": 729,
        "353": 403,
        "376": 671,
        "402": 591,
        "710": 500,
        "732": 500,
        "8211": 444,
        "8212": 575,
        "8216": 500,
        "8217": 194,
        "8218": 238,
        "8219": 500,
        "8220": 348,
        "8221": 348,
        "8222": 348,
        "8223": 500,
        "8224": 580,
        "8225": 580,
        "8226": 600,
        "8230": 721,
        "8240": 770,
        "8249": 286,
        "8250": 286,
        "8482": 977,
        "8729": 490,
        "57344": 490,
        "57345": 500,
        "57346": 667,
        "57347": 500,
        "57348": 500,
        "57349": 489,
        "57350": 667,
        "57351": 667,
        "57352": 542,
        "57353": 500,
        "57354": 734,
        "57355": 667,
        "57356": 500,
        "57357": 652,
        "57358": 667,
        "57359": 1426,
        "57360": 239,
        "57361": 500
    },
    "CIDtoGID_Compressed": true,
    "CIDtoGID": "eJzt0OWzb2UZx+EP3d3dIdIlINLdoaA0CAKioKSAdHfHobulpTulBAVURCUl\/wl+w5zhDee82GfY7IG5rpm1nmfW976fda9VXxmv8Qf3CQbXhE3UxE3SmE3aZE3eFE3ZVE3dNE3bdE3fDM3YTM3cLM3abM3eHM3ZXM3dPM3bfM3fAi3YQi3cIi3aD1qsH7Z4S7RkS7V0y7Rsy7V8K7RiP2qlVm6Vftyq\/aTVWr01WrO1Wrt1Wrf1Wr8N2rCN2rhN2rTN2rwt2rKt2rqf9rO2adt+3i\/aru3boR3bqZ3bpV3brV+2e3v0q\/Zsr\/bu1+3Tb\/rtWL5waE7spE7ulE7ttE7vjM7srM7unEFybud1fhd8WXVhF3Vxo7pksL+0y0b3Xt4VXdlVXd01Xdt1Xd8N3dhN3dwt3dpt\/WlQc3t3dGd3dXf3dG9\/7r7u74Ee7KFB9nCP9GiP9XhP9GRP9XTP9GzP9Xx\/6YVe7KVBzcu90l97tdf6W3\/v9d7ozf7RP\/vXIHvrG\/kDw+0PHT\/W7OCOHdJZJ4zD+\/cbhx4YqgOHUHv0cA0BAAAAAAAAAAAAAAAAAMB3wJEdNXp3aIe172A9vD\/2u8G6fwd0xOjs92PoPOhrTw7puGGZkZFyzEgPwLdo1EgPAAAAAAAAAAAAAAAAAAAAAAAAAAAAAAAAAAAAAAAAAAAAAAAAAAAAAAAAAAAAAAAAAAAAAAAAAAAAAAAAAAAAAAAAAAAAAAAAAAAAAAAAAAAAAAAAAAAAAAAAAAAAADCs\/t3b\/af\/9r\/e6d3e6\/0+6MP+30d93Cd92md9PtIjAgAAAAAAAAAAAAAAAAAAwPfdF0qybOw=",
    "_version_": 6
}